<?xml version="1.0" encoding="UTF-8"?>
<dealergroupDashboardDomain>

	<dealerGroupName>Dealer Group 3</dealerGroupName>
	<asAtDate>01 Oct 2013</asAtDate>
	<clientCount>679</clientCount>
	<accountCount>812</accountCount>
	<adviserCount>231</adviserCount>
	<fua>
		<totalCashAmount>$10,000,000</totalCashAmount>
		<totalTDAmount>$1,345,989</totalTDAmount>
		<totalFUA>$11,345,989</totalFUA>
		<noOfCashAccountsForThirtyDays>11</noOfCashAccountsForThirtyDays>
		<cashAccountsAmountForThirtyDays>$345,989</cashAccountsAmountForThirtyDays>
		<noOfTDAccountsForThirtyDays>7</noOfTDAccountsForThirtyDays>
		<totalTDAmountForThirtyDays>$145,000</totalTDAmountForThirtyDays>
		<changeInFUA>$999,096</changeInFUA>
		<cashAmountPercentage>88</cashAmountPercentage>
		<tdAmountPercentage>12</tdAmountPercentage>
	</fua>
	<termDepositsReport>
		<noOfAccounts>30</noOfAccounts>
		<totalPrinciple>$20,000</totalPrinciple>
		<totalPrincipleCashAccount>$900,405</totalPrincipleCashAccount>
		<totalPrincipleRollover>$200,408</totalPrincipleRollover>
		<totalPrincipleInterestRollover>$100,777</totalPrincipleInterestRollover>
		<totalOpenTermDeposits>10</totalOpenTermDeposits>
		<totalPrincipleOpenTermDeposits>$300,000</totalPrincipleOpenTermDeposits>
		<highestTermDeposit>$400,000</highestTermDeposit>
		<averageTermDeposit>$100,000</averageTermDeposit>
		<dealerGroupName>Dealer Group 3</dealerGroupName>
	</termDepositsReport>

</dealergroupDashboardDomain>