<?xml version="1.0" encoding="UTF-8" standalone="yes"?>
<rep:rep xmlns:rep="http://www.avaloq.com/abs/screen_rep/hira/btfg$ui_aal_list.aal#idx" xmlns:repb="http://www.avaloq.com/abs/screen_rep/base" xmlns:fldb="http://www.avaloq.com/abs/bb/fld_def" xmlns:xsi="http://www.w3.org/2001/XMLSchema-instance">
	<!-- 2016-06-03 16:52:24.127925000 on NGWD3 by AVALOQ -->
	<metadata>
		<empty_rep>
			<val>false</val>
		</empty_rep>
		<current_of_time>
			<val>2016-06-03T06:52:24+10:00</val>
		</current_of_time>
	</metadata>
	<def>
		<version>2.0</version>
		<rep_def>
			<style>flat</style>
			<lang id="1">en</lang>
			<hira_def>
				<grp_list>
					<grp_def>
						<name>dt</name>
						<hira>1</hira>
						<has_head>true</has_head>
						<has_foot>false</has_foot>
					</grp_def>
				</grp_list>
			</hira_def>
			<row_def>
				<fld_list>
					<fld_def>
						<name>idx</name>
						<type>TextFld</type>
						<lbl>Index</lbl>
					</fld_def>
					<fld_def>
						<name>aal</name>
						<type>TextFld</type>
						<lbl>Collection</lbl>
					</fld_def>
				</fld_list>
			</row_def>
		</rep_def>
	</def>
	<data>
		<dt_list>
			<dt>
				<dt_head_list>
					<dt_head id="2-1" row_type="data" hira="0" level="dt.head">
						<idx>
							<annot>
								<ctx>
									<type>idx</type>
									<id>163355</id>
								</ctx>
							</annot>
							<val>Standard (including Wholesale Plus)</val>
						</idx>
						<aal>
							<annot>
								<ctx>
									<type>collect</type>
									<id>28148</id>
								</ctx>
							</annot>
							<val>TD APL for Securitor Financial Group Limited</val>
						</aal>
					</dt_head>
					<dt_head id="4-2" row_type="data" hira="0" level="dt.head">
						<idx>
							<annot>
								<ctx>
									<type>idx</type>
									<id>205014</id>
								</ctx>
							</annot>
							<val>All Listed Securities</val>
						</idx>
						<aal>
							<annot>
								<ctx>
									<type>collect</type>
									<id>28148</id>
								</ctx>
							</annot>
							<val>TD APL for Securitor Financial Group Limited</val>
						</aal>
					</dt_head>
				</dt_head_list>
			</dt>
			<dt>
				<dt_head_list>
					<dt_head id="6-3" row_type="data" hira="0" level="dt.head">
						<idx>
							<annot>
								<ctx>
									<type>idx</type>
									<id>163355</id>
								</ctx>
							</annot>
							<val>Standard (including Wholesale Plus)</val>
						</idx>
						<aal>
							<annot>
								<ctx>
									<type>collect</type>
									<id>28154</id>
								</ctx>
							</annot>
							<val>TD APL for Professional Wealth Pty Ltd</val>
						</aal>
					</dt_head>
					<dt_head id="8-4" row_type="data" hira="0" level="dt.head">
						<idx>
							<annot>
								<ctx>
									<type>idx</type>
									<id>205014</id>
								</ctx>
							</annot>
							<val>All Listed Securities</val>
						</idx>
						<aal>
							<annot>
								<ctx>
									<type>collect</type>
									<id>28154</id>
								</ctx>
							</annot>
							<val>TD APL for Professional Wealth Pty Ltd</val>
						</aal>
					</dt_head>
				</dt_head_list>
			</dt>
			<dt>
				<dt_head_list>
					<dt_head id="10-5" row_type="data" hira="0" level="dt.head">
						<idx>
							<annot>
								<ctx>
									<type>idx</type>
									<id>163355</id>
								</ctx>
							</annot>
							<val>Standard (including Wholesale Plus)</val>
						</idx>
						<aal>
							<annot>
								<ctx>
									<type>collect</type>
									<id>32372</id>
								</ctx>
							</annot>
							<val>TD APL for Australian Financial Solutions Group</val>
						</aal>
					</dt_head>
					<dt_head id="12-6" row_type="data" hira="0" level="dt.head">
						<idx>
							<annot>
								<ctx>
									<type>idx</type>
									<id>205014</id>
								</ctx>
							</annot>
							<val>All Listed Securities</val>
						</idx>
						<aal>
							<annot>
								<ctx>
									<type>collect</type>
									<id>32372</id>
								</ctx>
							</annot>
							<val>TD APL for Australian Financial Solutions Group</val>
						</aal>
					</dt_head>
				</dt_head_list>
			</dt>
			<dt>
				<dt_head_list>
					<dt_head id="14-7" row_type="data" hira="0" level="dt.head">
						<idx>
							<annot>
								<ctx>
									<type>idx</type>
									<id>163355</id>
								</ctx>
							</annot>
							<val>Standard (including Wholesale Plus)</val>
						</idx>
						<aal>
							<annot>
								<ctx>
									<type>collect</type>
									<id>32475</id>
								</ctx>
							</annot>
							<val>TD APL for EXELSUPER ADVICE PTY LTD</val>
						</aal>
					</dt_head>
					<dt_head id="16-8" row_type="data" hira="0" level="dt.head">
						<idx>
							<annot>
								<ctx>
									<type>idx</type>
									<id>205014</id>
								</ctx>
							</annot>
							<val>All Listed Securities</val>
						</idx>
						<aal>
							<annot>
								<ctx>
									<type>collect</type>
									<id>32475</id>
								</ctx>
							</annot>
							<val>TD APL for EXELSUPER ADVICE PTY LTD</val>
						</aal>
					</dt_head>
				</dt_head_list>
			</dt>
			<dt>
				<dt_head_list>
					<dt_head id="18-9" row_type="data" hira="0" level="dt.head">
						<idx>
							<annot>
								<ctx>
									<type>idx</type>
									<id>163355</id>
								</ctx>
							</annot>
							<val>Standard (including Wholesale Plus)</val>
						</idx>
						<aal>
							<annot>
								<ctx>
									<type>collect</type>
									<id>35476</id>
								</ctx>
							</annot>
							<val>TD APL for Lonsdale Financial Group</val>
						</aal>
					</dt_head>
					<dt_head id="20-10" row_type="data" hira="0" level="dt.head">
						<idx>
							<annot>
								<ctx>
									<type>idx</type>
									<id>205014</id>
								</ctx>
							</annot>
							<val>All Listed Securities</val>
						</idx>
						<aal>
							<annot>
								<ctx>
									<type>collect</type>
									<id>35476</id>
								</ctx>
							</annot>
							<val>TD APL for Lonsdale Financial Group</val>
						</aal>
					</dt_head>
				</dt_head_list>
			</dt>
			<dt>
				<dt_head_list>
					<dt_head id="22-11" row_type="data" hira="0" level="dt.head">
						<idx>
							<annot>
								<ctx>
									<type>idx</type>
									<id>163355</id>
								</ctx>
							</annot>
							<val>Standard (including Wholesale Plus)</val>
						</idx>
						<aal>
							<annot>
								<ctx>
									<type>collect</type>
									<id>35581</id>
								</ctx>
							</annot>
							<val>TD APL for Advamode Financial Pty Ltd</val>
						</aal>
					</dt_head>
					<dt_head id="24-12" row_type="data" hira="0" level="dt.head">
						<idx>
							<annot>
								<ctx>
									<type>idx</type>
									<id>205014</id>
								</ctx>
							</annot>
							<val>All Listed Securities</val>
						</idx>
						<aal>
							<annot>
								<ctx>
									<type>collect</type>
									<id>35581</id>
								</ctx>
							</annot>
							<val>TD APL for Advamode Financial Pty Ltd</val>
						</aal>
					</dt_head>
				</dt_head_list>
			</dt>
			<dt>
				<dt_head_list>
					<dt_head id="26-13" row_type="data" hira="0" level="dt.head">
						<idx>
							<annot>
								<ctx>
									<type>idx</type>
									<id>163355</id>
								</ctx>
							</annot>
							<val>Standard (including Wholesale Plus)</val>
						</idx>
						<aal>
							<annot>
								<ctx>
									<type>collect</type>
									<id>36549</id>
								</ctx>
							</annot>
							<val>TD APL for Grant Thornton Wealth Advisory Services Pty Ltd</val>
						</aal>
					</dt_head>
					<dt_head id="28-14" row_type="data" hira="0" level="dt.head">
						<idx>
							<annot>
								<ctx>
									<type>idx</type>
									<id>205014</id>
								</ctx>
							</annot>
							<val>All Listed Securities</val>
						</idx>
						<aal>
							<annot>
								<ctx>
									<type>collect</type>
									<id>36549</id>
								</ctx>
							</annot>
							<val>TD APL for Grant Thornton Wealth Advisory Services Pty Ltd</val>
						</aal>
					</dt_head>
				</dt_head_list>
			</dt>
		</dt_list>
	</data>
</rep:rep>