<rep:rep xmlns:rep="http://www.avaloq.com/abs/screen_rep/hira/btfg$ui_cgt_unreal_bp_cont_assetgrp_asset" xmlns:repb="http://www.avaloq.com/abs/screen_rep/base" xmlns:fldb="http://www.avaloq.com/abs/bb/fld_def" xmlns:xsi="http://www.w3.org/2001/XMLSchema-instance">
	<!-- 2015-03-04 21:29:36.539195000 on afp010f by AVALOQ -->
	<metadata>
		<empty_rep>
			<val>false</val>
		</empty_rep>
		<ref_date>
			<val>2015-03-03</val>
		</ref_date>
		<tax_ccy_id>
			<val>1009</val>
		</tax_ccy_id>
		<current_of_time>
			<val>2015-03-04T10:29:36+11:00</val>
		</current_of_time>
	</metadata>
	<def>
		<version>2.0</version>
		<rep_def>
			<style>hira</style>
			<lang id="1">en</lang>
			<hira_def>
				<grp_list>
					<grp_def>
						<name>bp</name>
						<hira>1</hira>
						<has_head>true</has_head>
						<has_foot>false</has_foot>
					</grp_def>
					<grp_def>
						<name>cont_type</name>
						<hira>2</hira>
						<has_head>true</has_head>
						<has_foot>false</has_foot>
					</grp_def>
					<grp_def>
						<name>cont</name>
						<hira>3</hira>
						<has_head>true</has_head>
						<has_foot>false</has_foot>
					</grp_def>
					<grp_def>
						<name>asset_grp</name>
						<hira>4</hira>
						<has_head>true</has_head>
						<has_foot>false</has_foot>
					</grp_def>
					<grp_def>
						<name>asset</name>
						<hira>5</hira>
						<has_head>true</has_head>
						<has_foot>false</has_foot>
					</grp_def>
					<grp_def>
						<name>lot</name>
						<hira>6</hira>
						<has_head>true</has_head>
						<has_foot>false</has_foot>
					</grp_def>
				</grp_list>
			</hira_def>
			<row_def>
				<fld_list>
					<fld_def>
						<name>dummy</name>
						<type>TextFld</type>
						<lbl/>
					</fld_def>
					<fld_def>
						<name>bp_id</name>
						<type>NrFld</type>
						<lbl>BP ID</lbl>
					</fld_def>
					<fld_def>
						<name>dscnt_fact</name>
						<type>NrFld</type>
						<lbl>Discount factor</lbl>
					</fld_def>
					<fld_def>
						<name>cont_type_id</name>
						<type>NrFld</type>
						<lbl>Container type ID</lbl>
					</fld_def>
					<fld_def>
						<name>cont_id</name>
						<type>NrFld</type>
						<lbl>Container ID</lbl>
					</fld_def>
					<fld_def>
						<name>asset_grp_id</name>
						<type>NrFld</type>
						<lbl>Asset group ID</lbl>
					</fld_def>
					<fld_def>
						<name>asset_id</name>
						<type>NrFld</type>
						<lbl>Asset ID</lbl>
					</fld_def>
					<fld_def>
						<name>ref_asset_id</name>
						<type>NrFld</type>
						<lbl>Ref Asset ID</lbl>
					</fld_def>
					<fld_def>
						<name>price_date</name>
						<type>DateFld</type>
						<lbl>Last price date</lbl>
					</fld_def>
					<fld_def>
						<name>tax_date</name>
						<type>DateFld</type>
						<lbl>Tax date</lbl>
					</fld_def>
					<fld_def>
						<name>holding_period</name>
						<type>NrFld</type>
						<lbl>Days held</lbl>
					</fld_def>
					<fld_def>
						<name>qty</name>
						<type>NrFld</type>
						<lbl>Quantities held</lbl>
					</fld_def>
					<fld_def>
						<name>mkt_val_tc</name>
						<type>NrFld</type>
						<lbl>Market value</lbl>
					</fld_def>
					<fld_def>
						<name>tax_cost_tc</name>
						<type>NrFld</type>
						<lbl>Tax cost</lbl>
					</fld_def>
					<fld_def>
						<name>cb_tc</name>
						<type>NrFld</type>
						<lbl>Cost base</lbl>
					</fld_def>
					<fld_def>
						<name>rcb_tc</name>
						<type>NrFld</type>
						<lbl>Reduced cost base</lbl>
					</fld_def>
					<fld_def>
						<name>icb_tc</name>
						<type>NrFld</type>
						<lbl>Indexed cost base</lbl>
					</fld_def>
					<fld_def>
						<name>gain_loss_tc</name>
						<type>NrFld</type>
						<lbl>Gross gain/loss</lbl>
					</fld_def>
				</fld_list>
			</row_def>
		</rep_def>
	</def>
	<data>
		<bp_list>
			<bp>
				<bp_head_list>
					<bp_head id="2-1" row_type="title" hira="1" level="bp.head">
						<bp_id>
							<val>56979</val>
						</bp_id>
						<dscnt_fact>
							<val>.5</val>
						</dscnt_fact>
					</bp_head>
				</bp_head_list>
				<cont_type_list>
					<cont_type>
						<cont_type_head_list>
							<cont_type_head id="4-2" row_type="subtitle" hira="2" level="cont_type.head">
								<cont_type_id>
									<val>7102</val>
								</cont_type_id>
							</cont_type_head>
						</cont_type_head_list>
						<cont_list>
							<cont>
								<cont_head_list>
									<cont_head id="6-3" row_type="subtitle" hira="3" level="cont.head">
										<cont_id>
											<val>57090</val>
										</cont_id>
									</cont_head>
								</cont_head_list>
								<asset_grp_list>
									<asset_grp>
										<asset_grp_head_list>
											<asset_grp_head id="62-31" row_type="subtitle" hira="4" level="asset_grp.head">
												<asset_grp_id>
													<annot>
														<displ_text>Share</displ_text>
														<ctx>
															<type>code_obj_class</type>
															<id>10002</id>
														</ctx>
													</annot>
													<val>10002</val>
												</asset_grp_id>
											</asset_grp_head>
										</asset_grp_head_list>
										<asset_list>
											<asset>
												<asset_head_list>
													<asset_head id="70-35" row_type="subtitle" hira="5" level="asset.head">
														<asset_id>
															<annot>
																<displ_text>Charter Hall Retail Units</displ_text>
																<ctx>
																	<type>asset</type>
																	<id>110752</id>
																</ctx>
															</annot>
															<val>110752</val>
														</asset_id>
														<price_date>
															<val>2015-08-14</val>
														</price_date>
													</asset_head>
												</asset_head_list>
												<lot_list>
													<lot>
														<lot_head_list>
															<lot_head id="74-37" row_type="data" hira="6" level="lot.head">
																<tax_date>
																	<val>2015-03-30</val>
																</tax_date>
																<holding_period>
																	<val>154</val>
																</holding_period>
																<qty>
																	<val>6</val>
																</qty>
																<mkt_val_tc>
																	<val>25.08</val>
																</mkt_val_tc>
																<tax_cost_tc>
																	<val>25.8</val>
																</tax_cost_tc>
																<cb_tc>
																	<val>25.8</val>
																</cb_tc>
																<rcb_tc>
																	<val>25.8</val>
																</rcb_tc>
																<gain_loss_tc>
																	<val>-.73</val>
																</gain_loss_tc>
                                                                <gain_loss_cb>
                                                                    <val>-.73</val>
                                                                </gain_loss_cb>
                                                                <lot_status_id>
                                                                    <val>0</val>
                                                                </lot_status_id>
															</lot_head>
														</lot_head_list>
													</lot>
												</lot_list>
											</asset>
											<asset>
												<asset_head_list>
													<asset_head id="76-38" row_type="subtitle" hira="5" level="asset.head">
														<asset_id>
															<annot>
																<displ_text>Goodman Industrial Trust (Stapled Security Underlying)</displ_text>
																<ctx>
																	<type>asset</type>
																	<id>111297</id>
																</ctx>
															</annot>
															<val>111297</val>
														</asset_id>
														<ref_asset_id>
															<val>111412</val>
														</ref_asset_id>
														<price_date>
															<val>2015-01-01</val>
														</price_date>
													</asset_head>
												</asset_head_list>
												<lot_list>
													<lot>
														<lot_head_list>
															<lot_head id="78-39" row_type="data" hira="6" level="lot.head">
																<tax_date>
																	<val>2015-03-17</val>
																</tax_date>
																<holding_period>
																	<val>167</val>
																</holding_period>
																<qty>
																	<val>511</val>
																</qty>
																<mkt_val_tc>
																	<val>2906.57</val>
																</mkt_val_tc>
																<tax_cost_tc>
																	<val>2454.47</val>
																</tax_cost_tc>
																<cb_tc>
																	<val>2454.47</val>
																</cb_tc>
																<rcb_tc>
																	<val>2454.47</val>
																</rcb_tc>
																<gain_loss_tc>
																	<val>64.56</val>
																</gain_loss_tc>
                                                                <gain_loss_cb>
                                                                    <val>64.56</val>
                                                                </gain_loss_cb>
															</lot_head>
														</lot_head_list>
													</lot>
													<lot>
														<lot_head_list>
															<lot_head id="80-40" row_type="data" hira="6" level="lot.head">
																<tax_date>
																	<val>2015-03-30</val>
																</tax_date>
																<holding_period>
																	<val>154</val>
																</holding_period>
																<qty>
																	<val>37</val>
																</qty>
																<mkt_val_tc>
																	<val>210.46</val>
																</mkt_val_tc>
																<tax_cost_tc>
																	<val>179.43</val>
																</tax_cost_tc>
																<cb_tc>
																	<val>179.43</val>
																</cb_tc>
																<rcb_tc>
																	<val>179.43</val>
																</rcb_tc>
																<gain_loss_tc>
																	<val>2.97</val>
																</gain_loss_tc>
                                                                <gain_loss_cb>
                                                                    <val>2.97</val>
                                                                </gain_loss_cb>
															</lot_head>
														</lot_head_list>
													</lot>
												</lot_list>
											</asset>
											<asset>
												<asset_head_list>
													<asset_head id="88-44" row_type="subtitle" hira="5" level="asset.head">
														<asset_id>
															<annot>
																<displ_text>Goodman Logistics (Stapled Security Underlying)</displ_text>
																<ctx>
																	<type>asset</type>
																	<id>111299</id>
																</ctx>
															</annot>
															<val>111299</val>
														</asset_id>
														<ref_asset_id>
															<val>111412</val>
														</ref_asset_id>
														<price_date>
															<val>2014-12-25</val>
														</price_date>
													</asset_head>
												</asset_head_list>
												<lot_list>
													<lot>
														<lot_head_list>
															<lot_head id="90-45" row_type="data" hira="6" level="lot.head">
																<tax_date>
																	<val>2015-03-17</val>
																</tax_date>
																<holding_period>
																	<val>167</val>
																</holding_period>
																<qty>
																	<val>511</val>
																</qty>
																<mkt_val_tc>
																	<val>2906.57</val>
																</mkt_val_tc>
																<tax_cost_tc>
																	<val>377.61</val>
																</tax_cost_tc>
																<cb_tc>
																	<val>377.61</val>
																</cb_tc>
																<rcb_tc>
																	<val>377.61</val>
																</rcb_tc>
																<gain_loss_tc>
																	<val>9.93</val>
																</gain_loss_tc>
                                                                <gain_loss_cb>
                                                                    <val>9.93</val>
                                                                </gain_loss_cb>
															</lot_head>
														</lot_head_list>
													</lot>
													<lot>
														<lot_head_list>
															<lot_head id="92-46" row_type="data" hira="6" level="lot.head">
																<tax_date>
																	<val>2015-03-30</val>
																</tax_date>
																<holding_period>
																	<val>154</val>
																</holding_period>
																<qty>
																	<val>37</val>
																</qty>
																<mkt_val_tc>
																	<val>210.46</val>
																</mkt_val_tc>
																<tax_cost_tc>
																	<val>27.61</val>
																</tax_cost_tc>
																<cb_tc>
																	<val>27.61</val>
																</cb_tc>
																<rcb_tc>
																	<val>27.61</val>
																</rcb_tc>
																<gain_loss_tc>
																	<val>.45</val>
																</gain_loss_tc>
                                                                <gain_loss_cb>
                                                                    <val>.45</val>
                                                                </gain_loss_cb>
															</lot_head>
														</lot_head_list>
													</lot>
												</lot_list>
											</asset>
										</asset_list>
									</asset_grp>
									<asset_grp>
										<asset_grp_head_list>
											<asset_grp_head id="8-4" row_type="subtitle" hira="4" level="asset_grp.head">
												<asset_grp_id>
													<val>10005</val>
												</asset_grp_id>
											</asset_grp_head>
										</asset_grp_head_list>
										<asset_list>
											<asset>
												<asset_head_list>
													<asset_head id="10-5" row_type="subtitle" hira="5" level="asset.head">
														<asset_id>
															<val>93688</val>
														</asset_id>
														<price_date>
															<val>2014-12-21</val>
														</price_date>
													</asset_head>
												</asset_head_list>
												<lot_list>
													<lot>
														<lot_head_list>
															<lot_head id="12-6" row_type="data" hira="6" level="lot.head">
																<tax_date>
																	<val>2014-12-22</val>
																</tax_date>
																<holding_period>
																	<val>71</val>
																</holding_period>
																<qty>
																	<val>14825</val>
																</qty>
																<mkt_val_tc>
																	<val>0</val>
																</mkt_val_tc>
																<tax_cost_tc>
																	<val>13046</val>
																</tax_cost_tc>
																<cb_tc>
																	<val>13046</val>
																</cb_tc>
																<rcb_tc>
																	<val>13046</val>
																</rcb_tc>
																<gain_loss_tc>
																	<val>-13046</val>
																</gain_loss_tc>
                                                                <gain_loss_cb>
                                                                    <val>-13046</val>
                                                                </gain_loss_cb>
															</lot_head>
														</lot_head_list>
													</lot>
												</lot_list>
											</asset>
											<asset>
												<asset_head_list>
													<asset_head id="14-7" row_type="subtitle" hira="5" level="asset.head">
														<asset_id>
															<val>93692</val>
														</asset_id>
														<price_date>
															<val>2014-12-21</val>
														</price_date>
													</asset_head>
												</asset_head_list>
												<lot_list>
													<lot>
														<lot_head_list>
															<lot_head id="16-8" row_type="data" hira="6" level="lot.head">
																<tax_date>
																	<val>2014-12-22</val>
																</tax_date>
																<holding_period>
																	<val>71</val>
																</holding_period>
																<qty>
																	<val>1168.8312</val>
																</qty>
																<mkt_val_tc>
																	<val>0</val>
																</mkt_val_tc>
																<tax_cost_tc>
																	<val>981.82</val>
																</tax_cost_tc>
																<cb_tc>
																	<val>981.82</val>
																</cb_tc>
																<rcb_tc>
																	<val>981.82</val>
																</rcb_tc>
																<gain_loss_tc>
																	<val>-981.82</val>
																</gain_loss_tc>
                                                                <gain_loss_cb>
                                                                    <val>-981.82</val>
                                                                </gain_loss_cb>
															</lot_head>
														</lot_head_list>
													</lot>
												</lot_list>
											</asset>
											<asset>
												<asset_head_list>
													<asset_head id="18-9" row_type="subtitle" hira="5" level="asset.head">
														<asset_id>
															<val>93743</val>
														</asset_id>
														<price_date>
															<val>2014-12-21</val>
														</price_date>
													</asset_head>
												</asset_head_list>
												<lot_list>
													<lot>
														<lot_head_list>
															<lot_head id="20-10" row_type="data" hira="6" level="lot.head">
																<tax_date>
																	<val>2014-12-22</val>
																</tax_date>
																<holding_period>
																	<val>71</val>
																</holding_period>
																<qty>
																	<val>-500</val>
																</qty>
																<mkt_val_tc>
																	<val>0</val>
																</mkt_val_tc>
																<tax_cost_tc>
																	<val>-265</val>
																</tax_cost_tc>
																<cb_tc>
																	<val>-265</val>
																</cb_tc>
																<rcb_tc>
																	<val>-265</val>
																</rcb_tc>
																<gain_loss_tc>
																	<val>265</val>
																</gain_loss_tc>
                                                                <gain_loss_cb>
                                                                    <val>265</val>
                                                                </gain_loss_cb>
															</lot_head>
														</lot_head_list>
													</lot>
													<lot>
														<lot_head_list>
															<lot_head id="22-11" row_type="data" hira="6" level="lot.head">
																<tax_date>
																	<val>2014-12-22</val>
																</tax_date>
																<holding_period>
																	<val>71</val>
																</holding_period>
																<qty>
																	<val>-500</val>
																</qty>
																<mkt_val_tc>
																	<val>0</val>
																</mkt_val_tc>
																<tax_cost_tc>
																	<val>-2000</val>
																</tax_cost_tc>
																<cb_tc>
																	<val>-2000</val>
																</cb_tc>
																<rcb_tc>
																	<val>-2000</val>
																</rcb_tc>
																<gain_loss_tc>
																	<val>2000</val>
																</gain_loss_tc>
                                                                <gain_loss_cb>
                                                                    <val>2000</val>
                                                                </gain_loss_cb>
															</lot_head>
														</lot_head_list>
													</lot>
													<lot>
														<lot_head_list>
															<lot_head id="24-12" row_type="data" hira="6" level="lot.head">
																<tax_date>
																	<val>2014-12-22</val>
																</tax_date>
																<holding_period>
																	<val>71</val>
																</holding_period>
																<qty>
																	<val>-250</val>
																</qty>
																<mkt_val_tc>
																	<val>0</val>
																</mkt_val_tc>
																<tax_cost_tc>
																	<val>-1000</val>
																</tax_cost_tc>
																<cb_tc>
																	<val>-1000</val>
																</cb_tc>
																<rcb_tc>
																	<val>-1000</val>
																</rcb_tc>
																<gain_loss_tc>
																	<val>1000</val>
																</gain_loss_tc>
                                                                <gain_loss_cb>
                                                                    <val>1000</val>
                                                                </gain_loss_cb>
															</lot_head>
														</lot_head_list>
													</lot>
												</lot_list>
											</asset>
										</asset_list>
									</asset_grp>
								</asset_grp_list>
							</cont>
						</cont_list>
					</cont_type>
					<cont_type>
						<cont_type_head_list>
							<cont_type_head id="26-13" row_type="subtitle" hira="2" level="cont_type.head">
								<cont_type_id>
									<val>7105</val>
								</cont_type_id>
							</cont_type_head>
						</cont_type_head_list>
						<cont_list>
							<cont>
								<cont_head_list>
									<cont_head id="28-14" row_type="subtitle" hira="3" level="cont.head">
										<cont_id>
											<val>95467</val>
										</cont_id>
										<asset_id>
											<val>94339</val>
										</asset_id>
									</cont_head>
								</cont_head_list>
								<asset_grp_list>
									<asset_grp>
										<asset_grp_head_list>
											<asset_grp_head id="30-15" row_type="subtitle" hira="4" level="asset_grp.head">
												<asset_grp_id>
													<val>10002</val>
												</asset_grp_id>
											</asset_grp_head>
										</asset_grp_head_list>
										<asset_list>
											<asset>
												<asset_head_list>
													<asset_head id="32-16" row_type="subtitle" hira="5" level="asset.head">
														<asset_id>
															<val>92924</val>
														</asset_id>
														<price_date>
															<val>2014-12-19</val>
														</price_date>
													</asset_head>
												</asset_head_list>
												<lot_list>
													<lot>
														<lot_head_list>
															<lot_head id="34-17" row_type="data" hira="6" level="lot.head">
																<tax_date>
																	<val>2014-12-22</val>
																</tax_date>
																<holding_period>
																	<val>71</val>
																</holding_period>
																<qty>
																	<val>9000</val>
																</qty>
																<mkt_val_tc>
																	<val>0</val>
																</mkt_val_tc>
																<tax_cost_tc>
																	<val>4513.96</val>
																</tax_cost_tc>
																<cb_tc>
																	<val>4513.96</val>
																</cb_tc>
																<rcb_tc>
																	<val>4513.96</val>
																</rcb_tc>
																<gain_loss_tc>
																	<val>-4513.96</val>
																</gain_loss_tc>
                                                                <gain_loss_cb>
                                                                    <val>-4513.96</val>
                                                                </gain_loss_cb>
															</lot_head>
														</lot_head_list>
													</lot>
												</lot_list>
											</asset>
											<asset>
												<asset_head_list>
													<asset_head id="36-18" row_type="subtitle" hira="5" level="asset.head">
														<asset_id>
															<val>92928</val>
														</asset_id>
														<price_date>
															<val>2014-12-21</val>
														</price_date>
													</asset_head>
												</asset_head_list>
												<lot_list>
													<lot>
														<lot_head_list>
															<lot_head id="38-19" row_type="data" hira="6" level="lot.head">
																<tax_date>
																	<val>2014-12-22</val>
																</tax_date>
																<holding_period>
																	<val>71</val>
																</holding_period>
																<qty>
																	<val>3000</val>
																</qty>
																<mkt_val_tc>
																	<val>0</val>
																</mkt_val_tc>
																<tax_cost_tc>
																	<val>1651.82</val>
																</tax_cost_tc>
																<cb_tc>
																	<val>1651.82</val>
																</cb_tc>
																<rcb_tc>
																	<val>1651.82</val>
																</rcb_tc>
																<gain_loss_tc>
																	<val>-1651.82</val>
																</gain_loss_tc>
                                                                <gain_loss_cb>
                                                                    <val>-1651.82</val>
                                                                </gain_loss_cb>
															</lot_head>
														</lot_head_list>
													</lot>
												</lot_list>
											</asset>
											<asset>
												<asset_head_list>
													<asset_head id="40-20" row_type="subtitle" hira="5" level="asset.head">
														<asset_id>
															<val>93026</val>
														</asset_id>
														<price_date>
															<val>2014-12-12</val>
														</price_date>
													</asset_head>
												</asset_head_list>
												<lot_list>
													<lot>
														<lot_head_list>
															<lot_head id="42-21" row_type="data" hira="6" level="lot.head">
																<tax_date>
																	<val>2014-12-22</val>
																</tax_date>
																<holding_period>
																	<val>71</val>
																</holding_period>
																<qty>
																	<val>14900</val>
																</qty>
																<mkt_val_tc>
																	<val>0</val>
																</mkt_val_tc>
																<tax_cost_tc>
																	<val>14916.39</val>
																</tax_cost_tc>
																<cb_tc>
																	<val>14916.39</val>
																</cb_tc>
																<rcb_tc>
																	<val>14916.39</val>
																</rcb_tc>
																<gain_loss_tc>
																	<val>-14916.39</val>
																</gain_loss_tc>
                                                                <gain_loss_cb>
                                                                    <val>-14916.39</val>
                                                                </gain_loss_cb>
															</lot_head>
														</lot_head_list>
													</lot>
												</lot_list>
											</asset>
											<asset>
												<asset_head_list>
													<asset_head id="44-22" row_type="subtitle" hira="5" level="asset.head">
														<asset_id>
															<val>93101</val>
														</asset_id>
														<price_date>
															<val>2014-12-21</val>
														</price_date>
													</asset_head>
												</asset_head_list>
												<lot_list>
													<lot>
														<lot_head_list>
															<lot_head id="46-23" row_type="data" hira="6" level="lot.head">
																<tax_date>
																	<val>2014-12-22</val>
																</tax_date>
																<holding_period>
																	<val>71</val>
																</holding_period>
																<qty>
																	<val>1000</val>
																</qty>
																<mkt_val_tc>
																	<val>0</val>
																</mkt_val_tc>
																<tax_cost_tc>
																	<val>1001.1</val>
																</tax_cost_tc>
																<cb_tc>
																	<val>1001.1</val>
																</cb_tc>
																<rcb_tc>
																	<val>1001.1</val>
																</rcb_tc>
																<gain_loss_tc>
																	<val>-1001.1</val>
																</gain_loss_tc>
                                                                <gain_loss_cb>
                                                                    <val>-1001.1</val>
                                                                </gain_loss_cb>
															</lot_head>
														</lot_head_list>
													</lot>
												</lot_list>
											</asset>
										</asset_list>
									</asset_grp>
									<asset_grp>
										<asset_grp_head_list>
											<asset_grp_head id="48-24" row_type="subtitle" hira="4" level="asset_grp.head">
												<asset_grp_id>
													<val>10005</val>
												</asset_grp_id>
											</asset_grp_head>
										</asset_grp_head_list>
										<asset_list>
											<asset>
												<asset_head_list>
													<asset_head id="50-25" row_type="subtitle" hira="5" level="asset.head">
														<asset_id>
															<val>93659</val>
														</asset_id>
														<price_date>
															<val>2014-12-21</val>
														</price_date>
													</asset_head>
												</asset_head_list>
												<lot_list>
													<lot>
														<lot_head_list>
															<lot_head id="52-26" row_type="data" hira="6" level="lot.head">
																<tax_date>
																	<val>2014-11-02</val>
																</tax_date>
																<holding_period>
																	<val>121</val>
																</holding_period>
																<qty>
																	<val>1113.6364</val>
																</qty>
																<mkt_val_tc>
																	<val>0</val>
																</mkt_val_tc>
																<tax_cost_tc>
																	<val>1670.45</val>
																</tax_cost_tc>
																<cb_tc>
																	<val>1670.45</val>
																</cb_tc>
																<rcb_tc>
																	<val>1670.45</val>
																</rcb_tc>
																<gain_loss_tc>
																	<val>-1670.45</val>
																</gain_loss_tc>
                                                                <gain_loss_cb>
                                                                    <val>-1670.45</val>
                                                                </gain_loss_cb>
															</lot_head>
														</lot_head_list>
													</lot>
												</lot_list>
											</asset>
										</asset_list>
									</asset_grp>
								</asset_grp_list>
							</cont>
						</cont_list>
					</cont_type>
				</cont_type_list>
			</bp>
		</bp_list>
	</data>
</rep:rep>